{"cookies": [], "origins": [{"origin": "https://nikita-filonov.github.io", "localStorage": [{"name": "persist:users", "value": "{\"user\":\"{\\\"id\\\":\\\"aa182afa-5858-4ff0-b743-6b1b47ea7700\\\",\\\"email\\\":\\\"QwertyFire@gmail.com\\\",\\\"username\\\":\\\"Fire\\\",\\\"password\\\":\\\"1223_5678\\\"}\",\"users\":\"[{\\\"id\\\":\\\"aa182afa-5858-4ff0-b743-6b1b47ea7700\\\",\\\"email\\\":\\\"QwertyFire@gmail.com\\\",\\\"username\\\":\\\"Fire\\\",\\\"password\\\":\\\"1223_5678\\\"}]\",\"_persist\":\"{\\\"version\\\":-1,\\\"rehydrated\\\":true}\"}"}, {"name": "persist:courses", "value": "{\"course\":\"{\\\"id\\\":\\\"\\\",\\\"title\\\":\\\"\\\",\\\"userId\\\":\\\"\\\",\\\"maxScore\\\":0,\\\"minScore\\\":0,\\\"exercises\\\":[],\\\"description\\\":\\\"\\\",\\\"previewImage\\\":null,\\\"estimatedTime\\\":\\\"\\\"}\",\"courses\":\"[]\",\"_persist\":\"{\\\"version\\\":-1,\\\"rehydrated\\\":true}\"}"}]}]}